structured_logger/__init__.py
structured_logger/logger.py
structured_logger-1.0.4.dist-info/LICENSE
structured_logger-1.0.4.dist-info/METADATA
structured_logger-1.0.4.dist-info/WHEEL
structured_logger-1.0.4.dist-info/top_level.txt
structured_logger-1.0.4.dist-info/RECORD
