Metadata-Version: 2.1
Name: structured-logger
Version: 1.0.4
Summary: A small wrapper around the standard Python logger
Home-page: https://gitlab.com/dangerfarms/logger
Author: Danger Farms
Author-email: hello@dangerfarms.com
License: UNKNOWN
Platform: UNKNOWN
Classifier: Programming Language :: Python :: 3
Classifier: License :: OSI Approved :: MIT License
Classifier: Operating System :: OS Independent
Requires-Dist: simplejson
